video_transcriber/__init__.py
video_transcriber/transcribe.py
video_transcriber/adapters/__init__.py
video_transcriber/adapters/ffmpeg_audio.py
video_transcriber/adapters/opencv_video.py
video_transcriber/adapters/whisper_audio.py
video_transcriber/adapters/zip_markdown_report.py
video_transcriber/domain/__init__.py
video_transcriber/domain/frame_selector.py
video_transcriber/domain/models.py
video_transcriber/domain/video_transcriber.py
video_transcriber/ports/__init__.py
video_transcriber/ports/audio_extractor.py
video_transcriber/ports/audio_transcriber.py
video_transcriber/ports/video_reader.py
video_transcriber-0.3.1.dist-info/licenses/LICENSE
video_transcriber-0.3.1.dist-info/METADATA
video_transcriber-0.3.1.dist-info/WHEEL
video_transcriber-0.3.1.dist-info/top_level.txt
video_transcriber-0.3.1.dist-info/RECORD
