Metadata-Version: 2.4
Name: video-transcriber
Version: 0.3.1
Summary: A Python project following TDD principles
Author-email: Romilly Cocking <romilly.cocking@gmail.com>
License-Expression: MIT
Project-URL: Homepage, https://github.com/romilly/video-transcriber
Project-URL: Repository, https://github.com/romilly/video-transcriber.git
Project-URL: Issues, https://github.com/romilly/video-transcriber/issues
Classifier: Development Status :: 3 - Alpha
Classifier: Intended Audience :: Developers
Classifier: Programming Language :: Python :: 3
Classifier: Programming Language :: Python :: 3.8
Classifier: Programming Language :: Python :: 3.9
Classifier: Programming Language :: Python :: 3.10
Classifier: Programming Language :: Python :: 3.11
Classifier: Programming Language :: Python :: 3.12
Requires-Python: >=3.8
License-File: LICENSE
Requires-Dist: opencv-python
Requires-Dist: numpy
Requires-Dist: Pillow
Requires-Dist: faster-whisper
Provides-Extra: test
Requires-Dist: pytest>=7.0.0; extra == "test"
Requires-Dist: pytest-cov; extra == "test"
Requires-Dist: notebook; extra == "test"
Requires-Dist: build; extra == "test"
Dynamic: license-file
